src/ppe_serdes.v
`timescale 1ns/1ps

module ppe_serdes (
    input  wire       clk,
    input  wire       rst_n,
    
    // Config from CSR
    input  wire       cfg_enable,
    input  wire       cfg_bit_order,  // 0 = MSB-first, 1 = LSB-first
    
    // ==========================================
    // TX Path (SRAM FIFO -> Encoder)
    // ==========================================
    // Interface with TX FIFO
    input  wire [7:0] tx_byte_in,     // Byte from FIFO
    input  wire       tx_byte_valid,  // FIFO has valid byte
    output reg        tx_byte_pull,   // Pop next byte from FIFO (1 cycle pulse)
    
    // Interface with TX Encoder
    output wire       tx_bit_out,     // Current bit to encoder
    output reg        tx_bit_valid,   // SerDes has a valid bit to send
    input  wire       tx_bit_pull,    // Encoder consumes bit
    
    // ==========================================
    // RX Path (Decoder -> SRAM FIFO)
    // ==========================================
    // Interface with RX Decoder
    input  wire       rx_bit_in,
    input  wire       rx_bit_valid,
    
    // Interface with RX FIFO
    output reg  [7:0] rx_byte_out,
    output reg        rx_byte_push    // Push completed byte to FIFO
);

    // TX State
    reg [7:0] tx_shift_reg;
    reg [2:0] tx_bit_cnt;
    reg       tx_busy;

    // TX Bit Order Selection
    assign tx_bit_out = cfg_bit_order ? tx_shift_reg[0] : tx_shift_reg[7];

    always @(posedge clk or negedge rst_n) begin
        if (!rst_n) begin
            tx_shift_reg <= 8'd0;
            tx_bit_cnt   <= 3'd0;
            tx_busy      <= 1'b0;
            tx_byte_pull <= 1'b0;
            tx_bit_valid <= 1'b0;
        end else if (!cfg_enable) begin
            tx_shift_reg <= 8'd0;
            tx_bit_cnt   <= 3'd0;
            tx_busy      <= 1'b0;
            tx_byte_pull <= 1'b0;
            tx_bit_valid <= 1'b0;
        end else begin
            tx_byte_pull <= 1'b0; // Default to pulse
            
            if (!tx_busy) begin
                if (tx_byte_valid) begin
                    tx_shift_reg <= tx_byte_in;
                    tx_bit_cnt   <= 3'd0;
                    tx_busy      <= 1'b1;
                    tx_bit_valid <= 1'b1;
                    tx_byte_pull <= 1'b1; // Consume byte from FIFO
                end else begin
                    tx_bit_valid <= 1'b0;
                end
            end else begin
                if (tx_bit_pull) begin
                    // Encoder consumed the bit, shift next
                    if (tx_bit_cnt == 3'd7) begin
                        // Byte finished
                        tx_busy <= 1'b0;
                        tx_bit_valid <= 1'b0;
                    end else begin
                        tx_bit_cnt <= tx_bit_cnt + 1;
                        if (cfg_bit_order) // LSB-first
                            tx_shift_reg <= {1'b0, tx_shift_reg[7:1]};
                        else               // MSB-first
                            tx_shift_reg <= {tx_shift_reg[6:0], 1'b0};
                    end
                end
            end
        end
    end

    // RX State
    reg [7:0] rx_shift_reg;
    reg [2:0] rx_bit_cnt;
    reg [7:0] next_shift;

    always @(posedge clk or negedge rst_n) begin
        if (!rst_n) begin
            rx_shift_reg <= 8'd0;
            rx_bit_cnt   <= 3'd0;
            rx_byte_out  <= 8'd0;
            rx_byte_push <= 1'b0;
        end else if (!cfg_enable) begin
            rx_shift_reg <= 8'd0;
            rx_bit_cnt   <= 3'd0;
            rx_byte_out  <= 8'd0;
            rx_byte_push <= 1'b0;
        end else begin
            rx_byte_push <= 1'b0; // Default to pulse
            
            if (rx_bit_valid) begin
                // Shift in the new bit
                if (cfg_bit_order) // LSB-first
                    next_shift = {rx_bit_in, rx_shift_reg[7:1]};
                else               // MSB-first
                    next_shift = {rx_shift_reg[6:0], rx_bit_in};
                
                rx_shift_reg <= next_shift;
                
                if (rx_bit_cnt == 3'd7) begin
                    // Full byte received
                    rx_byte_out  <= next_shift;
                    rx_byte_push <= 1'b1;
                    rx_bit_cnt   <= 3'd0;
                end else begin
                    rx_bit_cnt <= rx_bit_cnt + 1;
                end
            end
        end
    end

endmodule

tb/ppe_serdes_tb.v
`timescale 1ns/1ps

module ppe_serdes_tb;

    reg clk;
    reg rst_n;
    
    // Config
    reg cfg_enable;
    reg cfg_bit_order;
    
    // TX Interface
    reg  [7:0] tx_byte_in;
    reg        tx_byte_valid;
    wire       tx_byte_pull;
    wire       tx_bit_out;
    wire       tx_bit_valid;
    reg        tx_bit_pull;
    
    // RX Interface
    reg        rx_bit_in;
    reg        rx_bit_valid;
    wire [7:0] rx_byte_out;
    wire       rx_byte_push;

    // DUT
    ppe_serdes dut (
        .clk(clk),
        .rst_n(rst_n),
        .cfg_enable(cfg_enable),
        .cfg_bit_order(cfg_bit_order),
        
        .tx_byte_in(tx_byte_in),
        .tx_byte_valid(tx_byte_valid),
        .tx_byte_pull(tx_byte_pull),
        
        .tx_bit_out(tx_bit_out),
        .tx_bit_valid(tx_bit_valid),
        .tx_bit_pull(tx_bit_pull),
        
        .rx_bit_in(rx_bit_in),
        .rx_bit_valid(rx_bit_valid),
        
        .rx_byte_out(rx_byte_out),
        .rx_byte_push(rx_byte_push)
    );

    // Clock Generation
    initial begin
        clk = 0;
        forever #10 clk = ~clk; // 50 MHz
    end

    initial begin
        $dumpfile("ppe_serdes.vcd");
        $dumpvars(0, ppe_serdes_tb);
        
        rst_n = 0;
        cfg_enable = 0;
        cfg_bit_order = 0;
        tx_byte_in = 0;
        tx_byte_valid = 0;
        tx_bit_pull = 0;
        rx_bit_in = 0;
        rx_bit_valid = 0;
        
        #100;
        rst_n = 1;
        #100;
        
        cfg_enable = 1;
        
        // ==========================================
        // TEST 1: TX Path (LSB First)
        // ==========================================
        $display("Starting TX Test (LSB First)");
        cfg_bit_order = 1; // LSB First
        
        // Present byte 0xA5 (1010_0101)
        tx_byte_in = 8'hA5;
        tx_byte_valid = 1;
        
        @(posedge clk);
        // Wait for SerDes to consume it
        while (!tx_byte_pull) @(posedge clk);
        tx_byte_valid = 0; // Clear it on next edge
        
        // Simulate encoder pulling 8 bits
        repeat(8) begin
            @(posedge clk);
            while (!tx_bit_valid) @(posedge clk);
            tx_bit_pull = 1;
            $display("TX Popped bit: %b", tx_bit_out);
            @(posedge clk);
            tx_bit_pull = 0;
            #20; // Some random wait between pulls
        end
        
        #100;
        
        // ==========================================
        // TEST 2: RX Path (MSB First)
        // ==========================================
        $display("Starting RX Test (MSB First)");
        cfg_bit_order = 0; // MSB First
        
        // Let's send 0x3C (0011_1100)
        send_rx_bit(0);
        send_rx_bit(0);
        send_rx_bit(1);
        send_rx_bit(1);
        
        send_rx_bit(1);
        send_rx_bit(1);
        send_rx_bit(0);
        send_rx_bit(0);
        
        @(posedge clk);
        if (rx_byte_push)
            $display("RX Pushed byte: %h", rx_byte_out);
            
        #100;
        $display("All Tests Completed.");
        $finish;
    end
    
    task send_rx_bit;
        input bit_val;
        begin
            @(posedge clk);
            rx_bit_in = bit_val;
            rx_bit_valid = 1;
            @(posedge clk);
            rx_bit_valid = 0;
            #30; // some time between bits
        end
    endtask

endmodule

tb/ppe_serdes.vcd
$date
	Fri Sep 18 18:28:58 2026
$end
$version
	Icarus Verilog
$end
$timescale
	1ps
$end
$scope module ppe_serdes_tb $end
$var wire 1 ! tx_byte_pull $end
$var wire 1 " tx_bit_valid $end
$var wire 1 # tx_bit_out $end
$var wire 1 $ rx_byte_push $end
$var wire 8 % rx_byte_out [7:0] $end
$var reg 1 & cfg_bit_order $end
$var reg 1 ' cfg_enable $end
$var reg 1 ( clk $end
$var reg 1 ) rst_n $end
$var reg 1 * rx_bit_in $end
$var reg 1 + rx_bit_valid $end
$var reg 1 , tx_bit_pull $end
$var reg 8 - tx_byte_in [7:0] $end
$var reg 1 . tx_byte_valid $end
$scope module dut $end
$var wire 1 & cfg_bit_order $end
$var wire 1 ' cfg_enable $end
$var wire 1 ( clk $end
$var wire 1 ) rst_n $end
$var wire 1 * rx_bit_in $end
$var wire 1 + rx_bit_valid $end
$var wire 1 , tx_bit_pull $end
$var wire 8 / tx_byte_in [7:0] $end
$var wire 1 . tx_byte_valid $end
$var wire 1 # tx_bit_out $end
$var reg 8 0 next_shift [7:0] $end
$var reg 3 1 rx_bit_cnt [2:0] $end
$var reg 8 2 rx_byte_out [7:0] $end
$var reg 1 $ rx_byte_push $end
$var reg 8 3 rx_shift_reg [7:0] $end
$var reg 3 4 tx_bit_cnt [2:0] $end
$var reg 1 " tx_bit_valid $end
$var reg 1 5 tx_busy $end
$var reg 1 ! tx_byte_pull $end
$var reg 8 6 tx_shift_reg [7:0] $end
$upscope $end
$scope task send_rx_bit $end
$var reg 1 7 bit_val $end
$upscope $end
$upscope $end
$enddefinitions $end
$comment Show the parameter values. $end
$dumpall
$end
#0
$dumpvars
x7
b0 6
05
b0 4
b0 3
b0 2
b0 1
bx 0
b0 /
0.
b0 -
0,
0+
0*
0)
0(
0'
0&
b0 %
0$
0#
0"
0!
$end
#10000
1(
#20000
0(
#30000
1(
#40000
0(
#50000
1(
#60000
0(
#70000
1(
#80000
0(
#90000
1(
#100000
0(
1)
#110000
1(
#120000
0(
#130000
1(
#140000
0(
#150000
1(
#160000
0(
#170000
1(
#180000
0(
#190000
1(
#200000
0(
1.
b10100101 -
b10100101 /
1&
1'
#210000
1#
1!
1"
15
b10100101 6
1(
#220000
0(
#230000
0!
0.
1(
#240000
0(
#250000
0#
b1010010 6
b1 4
1,
1(
#260000
0(
#270000
0,
1(
#280000
0(
#290000
1#
b101001 6
b10 4
1,
1(
#300000
0(
#310000
0,
1(
#320000
0(
#330000
0#
b10100 6
b11 4
1,
1(
#340000
0(
#350000
0,
1(
#360000
0(
#370000
b1010 6
b100 4
1,
1(
#380000
0(
#390000
0,
1(
#400000
0(
#410000
1#
b101 6
b101 4
1,
1(
#420000
0(
#430000
0,
1(
#440000
0(
#450000
0#
b10 6
b110 4
1,
1(
#460000
0(
#470000
0,
1(
#480000
0(
#490000
1#
b1 6
b111 4
1,
1(
#500000
0(
#510000
0,
1(
#520000
0(
#530000
0"
05
1,
1(
#540000
0(
#550000
0,
1(
#560000
0(
#570000
1(
#580000
0(
#590000
1(
#600000
0(
#610000
1(
#620000
0(
#630000
1(
#640000
0(
#650000
1(
#660000
0(
#670000
b1 1
b0 0
1+
0#
1(
07
0&
#680000
0(
#690000
0+
1(
#700000
0(
#710000
1(
#720000
0(
#730000
b10 1
1+
1(
#740000
0(
#750000
0+
1(
#760000
0(
#770000
1(
#780000
0(
17
#790000
b11 1
b1 3
b1 0
1+
1*
1(
#800000
0(
#810000
0+
1(
#820000
0(
#830000
1(
#840000
0(
#850000
b100 1
b11 3
b11 0
1+
1(
#860000
0(
#870000
0+
1(
#880000
0(
#890000
1(
#900000
0(
#910000
b101 1
b111 3
b111 0
1+
1(
#920000
0(
#930000
0+
1(
#940000
0(
#950000
1(
#960000
0(
#970000
b110 1
b1111 3
b1111 0
1+
1(
#980000
0(
#990000
0+
1(
#1000000
0(
#1010000
1(
#1020000
0(
07
#1030000
b111 1
b11110 3
b11110 0
1+
0*
1(
#1040000
0(
#1050000
0+
1(
#1060000
0(
#1070000
1(
#1080000
0(
#1090000
b0 1
1$
b111100 %
b111100 2
b111100 3
b111100 0
1+
1(
#1100000
0(
#1110000
0$
0+
1(
