src/ppe_rx_decoder.v
`timescale 1ns/1ps

module ppe_rx_decoder (
    input  wire       clk,
    input  wire       rst_n,
    
    // Config from CSRs
    input  wire       cfg_enable,
    input  wire [1:0] cfg_line_enc,   // 00=NRZ, 01=NRZI, 10=Manchester
    input  wire       cfg_stuff_en,
    input  wire [3:0] cfg_stuff_max,
    input  wire       cfg_stuff_val,
    input  wire       cfg_ins_val,
    
    // Timing
    input  wire       tick_8x,        // 8x oversampling tick
    
    // Interface from physical pins
    input  wire       rx_line_in,
    
    // Interface to Deserializer
    output reg        rx_bit_out,     // Decoded bit
    output reg        rx_valid        // 1-cycle pulse when rx_bit_out is valid
);

    reg [2:0] phase;
    reg       rx_sync;                // 1 when actively receiving
    reg       rx_last_pin;            // Edge detection
    reg       rx_last_sampled;        // For NRZI comparison
    reg       manchester_first_half;  // For Manchester decoding
    reg [3:0] stuff_cnt;
    reg       decoded_bit;

    wire edge_detected = (rx_line_in != rx_last_pin);

    always @(posedge clk or negedge rst_n) begin
        if (!rst_n) begin
            phase <= 3'd0;
            rx_sync <= 1'b0;
            rx_last_pin <= 1'b1; // Assume idle high
            rx_last_sampled <= 1'b1;
            manchester_first_half <= 1'b0;
            stuff_cnt <= 4'd0;
            rx_bit_out <= 1'b0;
            rx_valid <= 1'b0;
        end else if (!cfg_enable) begin
            phase <= 3'd0;
            rx_sync <= 1'b0;
            rx_last_pin <= rx_line_in;
            rx_last_sampled <= 1'b1;
            stuff_cnt <= 4'd0;
            rx_valid <= 1'b0;
        end else begin
            rx_valid <= 1'b0; // Default to 0 (pulse)
            rx_last_pin <= rx_line_in; // Track for edge detection

            if (tick_8x) begin
                if (edge_detected) begin
                    // Resynchronize DPLL on any edge
                    if (!rx_sync && cfg_line_enc != 2'b10) begin
                        // For NRZ/NRZI, first edge starts the frame
                        rx_sync <= 1'b1;
                    end
                    phase <= 3'd0; // Reset phase to align with edge
                end else begin
                    phase <= phase + 1;
                end

                // Sample in the middle of the bit period
                // For NRZ/NRZI: Sample at phase 4
                // For Manchester: Bit period is 2 edges. We sample at phase 2 and 6.
                if (cfg_line_enc != 2'b10) begin
                    // NRZ & NRZI Logic
                    if (rx_sync && phase == 3'd4) begin
                        // Line Decoding
                        if (cfg_line_enc == 2'b01) begin
                            // NRZI: transition = 0, no transition = 1
                            decoded_bit = (rx_line_in == rx_last_sampled) ? 1'b1 : 1'b0;
                        end else begin
                            // NRZ
                            decoded_bit = rx_line_in;
                        end
                        
                        rx_last_sampled <= rx_line_in;
                        
                        // Bit Unstuffing
                        if (cfg_stuff_en) begin
                            if (stuff_cnt == cfg_stuff_max) begin
                                // This SHOULD be the stuffed bit, ignore it and reset count
                                stuff_cnt <= 4'd0;
                            end else begin
                                rx_bit_out <= decoded_bit;
                                rx_valid   <= 1'b1;
                                if (decoded_bit == cfg_stuff_val)
                                    stuff_cnt <= stuff_cnt + 1;
                                else
                                    stuff_cnt <= 4'd0;
                            end
                        end else begin
                            rx_bit_out <= decoded_bit;
                            rx_valid   <= 1'b1;
                        end
                    end
                    
                    // Timeout/Loss of sync (idle detection)
                    if (rx_sync && phase == 3'd7 && rx_line_in == 1'b1 && !edge_detected) begin
                        // Simple timeout mechanism if line stays high (idle)
                        // In reality, higher level framing handles this better.
                    end
                    
                end else begin
                    // Manchester Logic (IEEE 802.3: 0->1 transition = 1, 1->0 transition = 0)
                    // The transition happens in the middle of the bit (phase 0 due to sync).
                    // This means the valid data is known right after the edge!
                    if (edge_detected) begin
                        rx_bit_out <= rx_line_in; // If it just went HIGH, it's a 1. If LOW, it's a 0.
                        rx_valid <= 1'b1;
                    end
                end
            end
        end
    end
endmodule

tb/ppe_rx_decoder_tb.v
`timescale 1ns/1ps

module ppe_rx_decoder_tb;

    reg clk;
    reg rst_n;
    
    // Config
    reg       cfg_enable;
    reg [1:0] cfg_line_enc;
    reg       cfg_stuff_en;
    reg [3:0] cfg_stuff_max;
    reg       cfg_stuff_val;
    reg       cfg_ins_val;
    
    // Timing
    reg tick_8x;
    
    // Inputs
    reg  rx_line_in;
    
    // Outputs
    wire rx_bit_out;
    wire rx_valid;

    // DUT
    ppe_rx_decoder dut (
        .clk(clk),
        .rst_n(rst_n),
        .cfg_enable(cfg_enable),
        .cfg_line_enc(cfg_line_enc),
        .cfg_stuff_en(cfg_stuff_en),
        .cfg_stuff_max(cfg_stuff_max),
        .cfg_stuff_val(cfg_stuff_val),
        .cfg_ins_val(cfg_ins_val),
        .tick_8x(tick_8x),
        .rx_line_in(rx_line_in),
        .rx_bit_out(rx_bit_out),
        .rx_valid(rx_valid)
    );

    // Clock Generation
    initial begin
        clk = 0;
        forever #10 clk = ~clk; // 50 MHz
    end

    // Tick Generation (8x oversampling)
    integer tick_div;
    always @(posedge clk) begin
        if (!rst_n) begin
            tick_div <= 0;
            tick_8x <= 0;
        end else begin
            if (tick_div == 3) begin // Arbitrary divider for test
                tick_div <= 0;
                tick_8x <= 1;
            end else begin
                tick_div <= tick_div + 1;
                tick_8x <= 0;
            end
        end
    end

    // Task to send a bit with 8 ticks of duration
    task send_line_state;
        input state;
        integer i;
        begin
            rx_line_in = state;
            for (i = 0; i < 8; i = i + 1) begin
                @(posedge clk);
                while (!tick_8x) @(posedge clk);
            end
        end
    endtask

    initial begin
        $dumpfile("ppe_rx_decoder.vcd");
        $dumpvars(0, ppe_rx_decoder_tb);
        
        rst_n = 0;
        cfg_enable = 0;
        cfg_line_enc = 2'b00;
        cfg_stuff_en = 0;
        cfg_stuff_max = 6;
        cfg_stuff_val = 1;
        cfg_ins_val = 0;
        rx_line_in = 1;
        
        #100;
        rst_n = 1;
        #100;
        
        // ==========================================
        // TEST 1: NRZ Mode (UART Style)
        // ==========================================
        $display("Starting Test 1: NRZ");
        cfg_enable = 1;
        cfg_line_enc = 2'b00;
        
        // Start bit (0)
        send_line_state(0);
        // Data bits (1, 0, 1)
        send_line_state(1);
        send_line_state(0);
        send_line_state(1);
        // Stop bit (1)
        send_line_state(1);
        
        #500;
        
        // ==========================================
        // TEST 2: NRZI + Bit Unstuffing (USB Style)
        // ==========================================
        $display("Starting Test 2: NRZI + Unstuffing");
        cfg_line_enc = 2'b01; // NRZI
        cfg_stuff_en = 1;
        
        // Reset line to idle J
        rx_line_in = 1;
        #500;
        
        // Let's send 7 consecutive '1's. In NRZI, this means NO transitions.
        // Wait, the encoder would have inserted a '0' (a transition) after 6 ones.
        // So line logic expected from TX:
        // Idle: 1
        // bit 1 (val 1): 1 (no trans)
        // bit 2 (val 1): 1
        // bit 3 (val 1): 1
        // bit 4 (val 1): 1
        // bit 5 (val 1): 1
        // bit 6 (val 1): 1
        // stuffed bit (0): 0 (transition!)
        // bit 7 (val 1): 0 (no trans)
        
        send_line_state(0); // Start packet (Sync edge)
        send_line_state(0); // 1 (val 1)
        send_line_state(0); // 2 (val 1)
        send_line_state(0); // 3 (val 1)
        send_line_state(0); // 4 (val 1)
        send_line_state(0); // 5 (val 1)
        send_line_state(0); // 6 (val 1)
        send_line_state(1); // STUFFED ZERO! (transition to 1)
        send_line_state(1); // 7 (val 1)
        
        #500;
        $display("All Tests Completed.");
        $finish;
    end

endmodule

tb/ppe_rx_decoder.vcd
$date
	Fri Sep 18 18:28:58 2026
$end
$version
	Icarus Verilog
$end
$timescale
	1ps
$end
$scope module ppe_rx_decoder_tb $end
$var wire 1 ! rx_valid $end
$var wire 1 " rx_bit_out $end
$var reg 1 # cfg_enable $end
$var reg 1 $ cfg_ins_val $end
$var reg 2 % cfg_line_enc [1:0] $end
$var reg 1 & cfg_stuff_en $end
$var reg 4 ' cfg_stuff_max [3:0] $end
$var reg 1 ( cfg_stuff_val $end
$var reg 1 ) clk $end
$var reg 1 * rst_n $end
$var reg 1 + rx_line_in $end
$var reg 1 , tick_8x $end
$var integer 32 - tick_div [31:0] $end
$scope module dut $end
$var wire 1 # cfg_enable $end
$var wire 1 $ cfg_ins_val $end
$var wire 2 . cfg_line_enc [1:0] $end
$var wire 1 & cfg_stuff_en $end
$var wire 4 / cfg_stuff_max [3:0] $end
$var wire 1 ( cfg_stuff_val $end
$var wire 1 ) clk $end
$var wire 1 0 edge_detected $end
$var wire 1 * rst_n $end
$var wire 1 + rx_line_in $end
$var wire 1 , tick_8x $end
$var reg 1 1 decoded_bit $end
$var reg 1 2 manchester_first_half $end
$var reg 3 3 phase [2:0] $end
$var reg 1 " rx_bit_out $end
$var reg 1 4 rx_last_pin $end
$var reg 1 5 rx_last_sampled $end
$var reg 1 6 rx_sync $end
$var reg 1 ! rx_valid $end
$var reg 4 7 stuff_cnt [3:0] $end
$upscope $end
$scope task send_line_state $end
$var reg 1 8 state $end
$var integer 32 9 i [31:0] $end
$upscope $end
$upscope $end
$enddefinitions $end
$comment Show the parameter values. $end
$dumpall
$end
#0
$dumpvars
bx 9
x8
b0 7
06
15
14
b0 3
02
x1
00
b110 /
b0 .
bx -
x,
1+
0*
0)
1(
b110 '
0&
b0 %
0$
0#
0"
0!
$end
#10000
0,
b0 -
1)
#20000
0)
#30000
1)
#40000
0)
#50000
1)
#60000
0)
#70000
1)
#80000
0)
#90000
1)
#100000
0)
1*
#110000
b1 -
1)
#120000
0)
#130000
b10 -
1)
#140000
0)
#150000
b11 -
1)
#160000
0)
#170000
1,
b0 -
1)
#180000
0)
#190000
0,
b1 -
1)
#200000
10
0)
b0 9
0+
08
1#
#210000
00
04
b10 -
1)
#220000
0)
#230000
b11 -
1)
#240000
0)
#250000
1,
b0 -
1)
#260000
0)
#270000
b1 3
0,
b1 -
b1 9
1)
#280000
0)
#290000
b10 -
1)
#300000
0)
#310000
b11 -
1)
#320000
0)
#330000
1,
b0 -
1)
#340000
0)
#350000
b10 3
0,
b1 -
b10 9
1)
#360000
0)
#370000
b10 -
1)
#380000
0)
#390000
b11 -
1)
#400000
0)
#410000
1,
b0 -
1)
#420000
0)
#430000
b11 3
0,
b1 -
b11 9
1)
#440000
0)
#450000
b10 -
1)
#460000
0)
#470000
b11 -
1)
#480000
0)
#490000
1,
b0 -
1)
#500000
0)
#510000
b100 3
0,
b1 -
b100 9
1)
#520000
0)
#530000
b10 -
1)
#540000
0)
#550000
b11 -
1)
#560000
0)
#570000
1,
b0 -
1)
#580000
0)
#590000
b101 3
0,
b1 -
b101 9
1)
#600000
0)
#610000
b10 -
1)
#620000
0)
#630000
b11 -
1)
#640000
0)
#650000
1,
b0 -
1)
#660000
0)
#670000
b110 3
0,
b1 -
b110 9
1)
#680000
0)
#690000
b10 -
1)
#700000
0)
#710000
b11 -
1)
#720000
0)
#730000
1,
b0 -
1)
#740000
0)
#750000
b111 3
0,
b1 -
b111 9
1)
#760000
0)
#770000
b10 -
1)
#780000
0)
#790000
b11 -
1)
#800000
0)
#810000
1,
b0 -
1)
#820000
0)
#830000
b0 3
14
0,
b1 -
00
1+
18
b0 9
1)
#840000
0)
#850000
b10 -
1)
#860000
0)
#870000
b11 -
1)
#880000
0)
#890000
1,
b0 -
1)
#900000
0)
#910000
b1 3
0,
b1 -
b1 9
1)
#920000
0)
#930000
b10 -
1)
#940000
0)
#950000
b11 -
1)
#960000
0)
#970000
1,
b0 -
1)
#980000
0)
#990000
b10 3
0,
b1 -
b10 9
1)
#1000000
0)
#1010000
b10 -
1)
#1020000
0)
#1030000
b11 -
1)
#1040000
0)
#1050000
1,
b0 -
1)
#1060000
0)
#1070000
b11 3
0,
b1 -
b11 9
1)
#1080000
0)
#1090000
b10 -
1)
#1100000
0)
#1110000
b11 -
1)
#1120000
0)
#1130000
1,
b0 -
1)
#1140000
0)
#1150000
b100 3
0,
b1 -
b100 9
1)
#1160000
0)
#1170000
b10 -
1)
#1180000
0)
#1190000
b11 -
1)
#1200000
0)
#1210000
1,
b0 -
1)
#1220000
0)
#1230000
b101 3
0,
b1 -
b101 9
1)
#1240000
0)
#1250000
b10 -
1)
#1260000
0)
#1270000
b11 -
1)
#1280000
0)
#1290000
1,
b0 -
1)
#1300000
0)
#1310000
b110 3
0,
b1 -
b110 9
1)
#1320000
0)
#1330000
b10 -
1)
#1340000
0)
#1350000
b11 -
1)
#1360000
0)
#1370000
1,
b0 -
1)
#1380000
0)
#1390000
b111 3
0,
b1 -
b111 9
1)
#1400000
0)
#1410000
b10 -
1)
#1420000
0)
#1430000
b11 -
1)
#1440000
0)
#1450000
1,
b0 -
1)
#1460000
0)
#1470000
b0 3
04
0,
b1 -
00
0+
08
b0 9
1)
#1480000
0)
#1490000
b10 -
1)
#1500000
0)
#1510000
b11 -
1)
#1520000
0)
#1530000
1,
b0 -
1)
#1540000
0)
#1550000
b1 3
0,
b1 -
b1 9
1)
#1560000
0)
#1570000
b10 -
1)
#1580000
0)
#1590000
b11 -
1)
#1600000
0)
#1610000
1,
b0 -
1)
#1620000
0)
#1630000
b10 3
0,
b1 -
b10 9
1)
#1640000
0)
#1650000
b10 -
1)
#1660000
0)
#1670000
b11 -
1)
#1680000
0)
#1690000
1,
b0 -
1)
#1700000
0)
#1710000
b11 3
0,
b1 -
b11 9
1)
#1720000
0)
#1730000
b10 -
1)
#1740000
0)
#1750000
b11 -
1)
#1760000
0)
#1770000
1,
b0 -
1)
#1780000
0)
#1790000
b100 3
0,
b1 -
b100 9
1)
#1800000
0)
#1810000
b10 -
1)
#1820000
0)
#1830000
b11 -
1)
#1840000
0)
#1850000
1,
b0 -
1)
#1860000
0)
#1870000
b101 3
0,
b1 -
b101 9
1)
#1880000
0)
#1890000
b10 -
1)
#1900000
0)
#1910000
b11 -
1)
#1920000
0)
#1930000
1,
b0 -
1)
#1940000
0)
#1950000
b110 3
0,
b1 -
b110 9
1)
#1960000
0)
#1970000
b10 -
1)
#1980000
0)
#1990000
b11 -
1)
#2000000
0)
#2010000
1,
b0 -
1)
#2020000
0)
#2030000
b111 3
0,
b1 -
b111 9
1)
#2040000
0)
#2050000
b10 -
1)
#2060000
0)
#2070000
b11 -
1)
#2080000
0)
#2090000
1,
b0 -
1)
#2100000
0)
#2110000
b0 3
14
0,
b1 -
00
1+
18
b0 9
1)
#2120000
0)
#2130000
b10 -
1)
#2140000
0)
#2150000
b11 -
1)
#2160000
0)
#2170000
1,
b0 -
1)
#2180000
0)
#2190000
b1 3
0,
b1 -
b1 9
1)
#2200000
0)
#2210000
b10 -
1)
#2220000
0)
#2230000
b11 -
1)
#2240000
0)
#2250000
1,
b0 -
1)
#2260000
0)
#2270000
b10 3
0,
b1 -
b10 9
1)
#2280000
0)
#2290000
b10 -
1)
#2300000
0)
#2310000
b11 -
1)
#2320000
0)
#2330000
1,
b0 -
1)
#2340000
0)
#2350000
b11 3
0,
b1 -
b11 9
1)
#2360000
0)
#2370000
b10 -
1)
#2380000
0)
#2390000
b11 -
1)
#2400000
0)
#2410000
1,
b0 -
1)
#2420000
0)
#2430000
b100 3
0,
b1 -
b100 9
1)
#2440000
0)
#2450000
b10 -
1)
#2460000
0)
#2470000
b11 -
1)
#2480000
0)
#2490000
1,
b0 -
1)
#2500000
0)
#2510000
b101 3
0,
b1 -
b101 9
1)
#2520000
0)
#2530000
b10 -
1)
#2540000
0)
#2550000
b11 -
1)
#2560000
0)
#2570000
1,
b0 -
1)
#2580000
0)
#2590000
b110 3
0,
b1 -
b110 9
1)
#2600000
0)
#2610000
b10 -
1)
#2620000
0)
#2630000
b11 -
1)
#2640000
0)
#2650000
1,
b0 -
1)
#2660000
0)
#2670000
b111 3
0,
b1 -
b111 9
1)
#2680000
0)
#2690000
b10 -
1)
#2700000
0)
#2710000
b11 -
1)
#2720000
0)
#2730000
1,
b0 -
1)
#2740000
0)
#2750000
b0 3
0,
b1 -
b0 9
1)
#2760000
0)
#2770000
b10 -
1)
#2780000
0)
#2790000
b11 -
1)
#2800000
0)
#2810000
1,
b0 -
1)
#2820000
0)
#2830000
b1 3
0,
b1 -
b1 9
1)
#2840000
0)
#2850000
b10 -
1)
#2860000
0)
#2870000
b11 -
1)
#2880000
0)
#2890000
1,
b0 -
1)
#2900000
0)
#2910000
b10 3
0,
b1 -
b10 9
1)
#2920000
0)
#2930000
b10 -
1)
#2940000
0)
#2950000
b11 -
1)
#2960000
0)
#2970000
1,
b0 -
1)
#2980000
0)
#2990000
b11 3
0,
b1 -
b11 9
1)
#3000000
0)
#3010000
b10 -
1)
#3020000
0)
#3030000
b11 -
1)
#3040000
0)
#3050000
1,
b0 -
1)
#3060000
0)
#3070000
b100 3
0,
b1 -
b100 9
1)
#3080000
0)
#3090000
b10 -
1)
#3100000
0)
#3110000
b11 -
1)
#3120000
0)
#3130000
1,
b0 -
1)
#3140000
0)
#3150000
b101 3
0,
b1 -
b101 9
1)
#3160000
0)
#3170000
b10 -
1)
#3180000
0)
#3190000
b11 -
1)
#3200000
0)
#3210000
1,
b0 -
1)
#3220000
0)
#3230000
b110 3
0,
b1 -
b110 9
1)
#3240000
0)
#3250000
b10 -
1)
#3260000
0)
#3270000
b11 -
1)
#3280000
0)
#3290000
1,
b0 -
1)
#3300000
0)
#3310000
b111 3
0,
b1 -
b111 9
1)
#3320000
0)
#3330000
b10 -
1)
#3340000
0)
#3350000
b11 -
1)
#3360000
0)
#3370000
1,
b0 -
1)
#3380000
0)
#3390000
b0 3
0,
b1 -
b1000 9
1)
#3400000
0)
#3410000
b10 -
1)
#3420000
0)
#3430000
b11 -
1)
#3440000
0)
#3450000
1,
b0 -
1)
#3460000
0)
#3470000
b1 3
0,
b1 -
1)
#3480000
0)
#3490000
b10 -
1)
#3500000
0)
#3510000
b11 -
1)
#3520000
0)
#3530000
1,
b0 -
1)
#3540000
0)
#3550000
b10 3
0,
b1 -
1)
#3560000
0)
#3570000
b10 -
1)
#3580000
0)
#3590000
b11 -
1)
#3600000
0)
#3610000
1,
b0 -
1)
#3620000
0)
#3630000
b11 3
0,
b1 -
1)
#3640000
0)
#3650000
b10 -
1)
#3660000
0)
#3670000
b11 -
1)
#3680000
0)
#3690000
1,
b0 -
1)
#3700000
0)
#3710000
b100 3
0,
b1 -
1)
#3720000
0)
#3730000
b10 -
1)
#3740000
0)
#3750000
b11 -
1)
#3760000
0)
#3770000
1,
b0 -
1)
#3780000
0)
#3790000
b101 3
0,
b1 -
1)
#3800000
0)
#3810000
b10 -
1)
#3820000
0)
#3830000
b11 -
1)
#3840000
0)
#3850000
1,
b0 -
1)
#3860000
0)
#3870000
b110 3
0,
b1 -
1)
#3880000
0)
#3890000
b10 -
1)
1&
b1 %
b1 .
#3900000
0)
#3910000
b11 -
1)
#3920000
0)
#3930000
1,
b0 -
1)
#3940000
0)
#3950000
b111 3
0,
b1 -
1)
#3960000
0)
#3970000
b10 -
1)
#3980000
0)
#3990000
b11 -
1)
#4000000
0)
#4010000
1,
b0 -
1)
#4020000
0)
#4030000
b0 3
0,
b1 -
1)
#4040000
0)
#4050000
b10 -
1)
#4060000
0)
#4070000
b11 -
1)
#4080000
0)
#4090000
1,
b0 -
1)
#4100000
0)
#4110000
b1 3
0,
b1 -
1)
#4120000
0)
#4130000
b10 -
1)
#4140000
0)
#4150000
b11 -
1)
#4160000
0)
#4170000
1,
b0 -
1)
#4180000
0)
#4190000
b10 3
0,
b1 -
1)
#4200000
0)
#4210000
b10 -
1)
#4220000
0)
#4230000
b11 -
1)
#4240000
0)
#4250000
1,
b0 -
1)
#4260000
0)
#4270000
b11 3
0,
b1 -
1)
#4280000
0)
#4290000
b10 -
1)
#4300000
0)
#4310000
b11 -
1)
#4320000
0)
#4330000
1,
b0 -
1)
#4340000
0)
#4350000
b100 3
0,
b1 -
1)
#4360000
0)
#4370000
b10 -
1)
#4380000
0)
#4390000
04
b11 -
00
1)
b0 9
0+
08
#4400000
0)
#4410000
1,
b0 -
1)
#4420000
0)
#4430000
b101 3
0,
b1 -
b1 9
1)
#4440000
0)
#4450000
b10 -
1)
#4460000
0)
#4470000
b11 -
1)
#4480000
0)
#4490000
1,
b0 -
1)
#4500000
0)
#4510000
b110 3
0,
b1 -
b10 9
1)
#4520000
0)
#4530000
b10 -
1)
#4540000
0)
#4550000
b11 -
1)
#4560000
0)
#4570000
1,
b0 -
1)
#4580000
0)
#4590000
b111 3
0,
b1 -
b11 9
1)
#4600000
0)
#4610000
b10 -
1)
#4620000
0)
#4630000
b11 -
1)
#4640000
0)
#4650000
1,
b0 -
1)
#4660000
0)
#4670000
b0 3
0,
b1 -
b100 9
1)
#4680000
0)
#4690000
b10 -
1)
#4700000
0)
#4710000
b11 -
1)
#4720000
0)
#4730000
1,
b0 -
1)
#4740000
0)
#4750000
b1 3
0,
b1 -
b101 9
1)
#4760000
0)
#4770000
b10 -
1)
#4780000
0)
#4790000
b11 -
1)
#4800000
0)
#4810000
1,
b0 -
1)
#4820000
0)
#4830000
b10 3
0,
b1 -
b110 9
1)
#4840000
0)
#4850000
b10 -
1)
#4860000
0)
#4870000
b11 -
1)
#4880000
0)
#4890000
1,
b0 -
1)
#4900000
0)
#4910000
b11 3
0,
b1 -
b111 9
1)
#4920000
0)
#4930000
b10 -
1)
#4940000
0)
#4950000
b11 -
1)
#4960000
0)
#4970000
1,
b0 -
1)
#4980000
0)
#4990000
b100 3
0,
b1 -
b0 9
1)
#5000000
0)
#5010000
b10 -
1)
#5020000
0)
#5030000
b11 -
1)
#5040000
0)
#5050000
1,
b0 -
1)
#5060000
0)
#5070000
b101 3
0,
b1 -
b1 9
1)
#5080000
0)
#5090000
b10 -
1)
#5100000
0)
#5110000
b11 -
1)
#5120000
0)
#5130000
1,
b0 -
1)
#5140000
0)
#5150000
b110 3
0,
b1 -
b10 9
1)
#5160000
0)
#5170000
b10 -
1)
#5180000
0)
#5190000
b11 -
1)
#5200000
0)
#5210000
1,
b0 -
1)
#5220000
0)
#5230000
b111 3
0,
b1 -
b11 9
1)
#5240000
0)
#5250000
b10 -
1)
#5260000
0)
#5270000
b11 -
1)
#5280000
0)
#5290000
1,
b0 -
1)
#5300000
0)
#5310000
b0 3
0,
b1 -
b100 9
1)
#5320000
0)
#5330000
b10 -
1)
#5340000
0)
#5350000
b11 -
1)
#5360000
0)
#5370000
1,
b0 -
1)
#5380000
0)
#5390000
b1 3
0,
b1 -
b101 9
1)
#5400000
0)
#5410000
b10 -
1)
#5420000
0)
#5430000
b11 -
1)
#5440000
0)
#5450000
1,
b0 -
1)
#5460000
0)
#5470000
b10 3
0,
b1 -
b110 9
1)
#5480000
0)
#5490000
b10 -
1)
#5500000
0)
#5510000
b11 -
1)
#5520000
0)
#5530000
1,
b0 -
1)
#5540000
0)
#5550000
b11 3
0,
b1 -
b111 9
1)
#5560000
0)
#5570000
b10 -
1)
#5580000
0)
#5590000
b11 -
1)
#5600000
0)
#5610000
1,
b0 -
1)
#5620000
0)
#5630000
b100 3
0,
b1 -
b0 9
1)
#5640000
0)
#5650000
b10 -
1)
#5660000
0)
#5670000
b11 -
1)
#5680000
0)
#5690000
1,
b0 -
1)
#5700000
0)
#5710000
b101 3
0,
b1 -
b1 9
1)
#5720000
0)
#5730000
b10 -
1)
#5740000
0)
#5750000
b11 -
1)
#5760000
0)
#5770000
1,
b0 -
1)
#5780000
0)
#5790000
b110 3
0,
b1 -
b10 9
1)
#5800000
0)
#5810000
b10 -
1)
#5820000
0)
#5830000
b11 -
1)
#5840000
0)
#5850000
1,
b0 -
1)
#5860000
0)
#5870000
b111 3
0,
b1 -
b11 9
1)
#5880000
0)
#5890000
b10 -
1)
#5900000
0)
#5910000
b11 -
1)
#5920000
0)
#5930000
1,
b0 -
1)
#5940000
0)
#5950000
b0 3
0,
b1 -
b100 9
1)
#5960000
0)
#5970000
b10 -
1)
#5980000
0)
#5990000
b11 -
1)
#6000000
0)
#6010000
1,
b0 -
1)
#6020000
0)
#6030000
b1 3
0,
b1 -
b101 9
1)
#6040000
0)
#6050000
b10 -
1)
#6060000
0)
#6070000
b11 -
1)
#6080000
0)
#6090000
1,
b0 -
1)
#6100000
0)
#6110000
b10 3
0,
b1 -
b110 9
1)
#6120000
0)
#6130000
b10 -
1)
#6140000
0)
#6150000
b11 -
1)
#6160000
0)
#6170000
1,
b0 -
1)
#6180000
0)
#6190000
b11 3
0,
b1 -
b111 9
1)
#6200000
0)
#6210000
b10 -
1)
#6220000
0)
#6230000
b11 -
1)
#6240000
0)
#6250000
1,
b0 -
1)
#6260000
0)
#6270000
b100 3
0,
b1 -
b0 9
1)
#6280000
0)
#6290000
b10 -
1)
#6300000
0)
#6310000
b11 -
1)
#6320000
0)
#6330000
1,
b0 -
1)
#6340000
0)
#6350000
b101 3
0,
b1 -
b1 9
1)
#6360000
0)
#6370000
b10 -
1)
#6380000
0)
#6390000
b11 -
1)
#6400000
0)
#6410000
1,
b0 -
1)
#6420000
0)
#6430000
b110 3
0,
b1 -
b10 9
1)
#6440000
0)
#6450000
b10 -
1)
#6460000
0)
#6470000
b11 -
1)
#6480000
0)
#6490000
1,
b0 -
1)
#6500000
0)
#6510000
b111 3
0,
b1 -
b11 9
1)
#6520000
0)
#6530000
b10 -
1)
#6540000
0)
#6550000
b11 -
1)
#6560000
0)
#6570000
1,
b0 -
1)
#6580000
0)
#6590000
b0 3
0,
b1 -
b100 9
1)
#6600000
0)
#6610000
b10 -
1)
#6620000
0)
#6630000
b11 -
1)
#6640000
0)
#6650000
1,
b0 -
1)
#6660000
0)
#6670000
b1 3
0,
b1 -
b101 9
1)
#6680000
0)
#6690000
b10 -
1)
#6700000
0)
#6710000
b11 -
1)
#6720000
0)
#6730000
1,
b0 -
1)
#6740000
0)
#6750000
b10 3
0,
b1 -
b110 9
1)
#6760000
0)
#6770000
b10 -
1)
#6780000
0)
#6790000
b11 -
1)
#6800000
0)
#6810000
1,
b0 -
1)
#6820000
0)
#6830000
b11 3
0,
b1 -
b111 9
1)
#6840000
0)
#6850000
b10 -
1)
#6860000
0)
#6870000
b11 -
1)
#6880000
0)
#6890000
1,
b0 -
1)
#6900000
0)
#6910000
b100 3
0,
b1 -
b0 9
1)
#6920000
0)
#6930000
b10 -
1)
#6940000
0)
#6950000
b11 -
1)
#6960000
0)
#6970000
1,
b0 -
1)
#6980000
0)
#6990000
b101 3
0,
b1 -
b1 9
1)
#7000000
0)
#7010000
b10 -
1)
#7020000
0)
#7030000
b11 -
1)
#7040000
0)
#7050000
1,
b0 -
1)
#7060000
0)
#7070000
b110 3
0,
b1 -
b10 9
1)
#7080000
0)
#7090000
b10 -
1)
#7100000
0)
#7110000
b11 -
1)
#7120000
0)
#7130000
1,
b0 -
1)
#7140000
0)
#7150000
b111 3
0,
b1 -
b11 9
1)
#7160000
0)
#7170000
b10 -
1)
#7180000
0)
#7190000
b11 -
1)
#7200000
0)
#7210000
1,
b0 -
1)
#7220000
0)
#7230000
b0 3
0,
b1 -
b100 9
1)
#7240000
0)
#7250000
b10 -
1)
#7260000
0)
#7270000
b11 -
1)
#7280000
0)
#7290000
1,
b0 -
1)
#7300000
0)
#7310000
b1 3
0,
b1 -
b101 9
1)
#7320000
0)
#7330000
b10 -
1)
#7340000
0)
#7350000
b11 -
1)
#7360000
0)
#7370000
1,
b0 -
1)
#7380000
0)
#7390000
b10 3
0,
b1 -
b110 9
1)
#7400000
0)
#7410000
b10 -
1)
#7420000
0)
#7430000
b11 -
1)
#7440000
0)
#7450000
1,
b0 -
1)
#7460000
0)
#7470000
b11 3
0,
b1 -
b111 9
1)
#7480000
0)
#7490000
b10 -
1)
#7500000
0)
#7510000
b11 -
1)
#7520000
0)
#7530000
1,
b0 -
1)
#7540000
0)
#7550000
b100 3
0,
b1 -
b0 9
1)
#7560000
0)
#7570000
b10 -
1)
#7580000
0)
#7590000
b11 -
1)
#7600000
0)
#7610000
1,
b0 -
1)
#7620000
0)
#7630000
b101 3
0,
b1 -
b1 9
1)
#7640000
0)
#7650000
b10 -
1)
#7660000
0)
#7670000
b11 -
1)
#7680000
0)
#7690000
1,
b0 -
1)
#7700000
0)
#7710000
b110 3
0,
b1 -
b10 9
1)
#7720000
0)
#7730000
b10 -
1)
#7740000
0)
#7750000
b11 -
1)
#7760000
0)
#7770000
1,
b0 -
1)
#7780000
0)
#7790000
b111 3
0,
b1 -
b11 9
1)
#7800000
0)
#7810000
b10 -
1)
#7820000
0)
#7830000
b11 -
1)
#7840000
0)
#7850000
1,
b0 -
1)
#7860000
0)
#7870000
b0 3
0,
b1 -
b100 9
1)
#7880000
0)
#7890000
b10 -
1)
#7900000
0)
#7910000
b11 -
1)
#7920000
0)
#7930000
1,
b0 -
1)
#7940000
0)
#7950000
b1 3
0,
b1 -
b101 9
1)
#7960000
0)
#7970000
b10 -
1)
#7980000
0)
#7990000
b11 -
1)
#8000000
0)
#8010000
1,
b0 -
1)
#8020000
0)
#8030000
b10 3
0,
b1 -
b110 9
1)
#8040000
0)
#8050000
b10 -
1)
#8060000
0)
#8070000
b11 -
1)
#8080000
0)
#8090000
1,
b0 -
1)
#8100000
0)
#8110000
b11 3
0,
b1 -
b111 9
1)
#8120000
0)
#8130000
b10 -
1)
#8140000
0)
#8150000
b11 -
1)
#8160000
0)
#8170000
1,
b0 -
1)
#8180000
0)
#8190000
b100 3
0,
b1 -
b0 9
1)
#8200000
0)
#8210000
b10 -
1)
#8220000
0)
#8230000
b11 -
1)
#8240000
0)
#8250000
1,
b0 -
1)
#8260000
0)
#8270000
b101 3
0,
b1 -
b1 9
1)
#8280000
0)
#8290000
b10 -
1)
#8300000
0)
#8310000
b11 -
1)
#8320000
0)
#8330000
1,
b0 -
1)
#8340000
0)
#8350000
b110 3
0,
b1 -
b10 9
1)
#8360000
0)
#8370000
b10 -
1)
#8380000
0)
#8390000
b11 -
1)
#8400000
0)
#8410000
1,
b0 -
1)
#8420000
0)
#8430000
b111 3
0,
b1 -
b11 9
1)
#8440000
0)
#8450000
b10 -
1)
#8460000
0)
#8470000
b11 -
1)
#8480000
0)
